README.rst
setup.py
snakemakeutils.py
snakemakeutils.egg-info/PKG-INFO
snakemakeutils.egg-info/SOURCES.txt
snakemakeutils.egg-info/dependency_links.txt
snakemakeutils.egg-info/requires.txt
snakemakeutils.egg-info/top_level.txt