Metadata-Version: 1.1
Name: snakemakeutils
Version: 0.1.2
Summary: Snakemake utils
Home-page: https://github.com/igordejanovic/snakemakeutils
Author: Igor R. Dejanovic
Author-email: igor DOT dejanovic AT gmail DOT com
License: MIT
Download-URL: https://github.com/igordejanovic/snakemakeutils/archive/v0.1.2.tar.gz
Keywords: make utils helper
Platform: UNKNOWN
Classifier: Development Status :: 3 - Alpha
Classifier: Intended Audience :: Developers
Classifier: Intended Audience :: Information Technology
Classifier: Intended Audience :: Science/Research
Classifier: Topic :: Software Development :: Libraries :: Python Modules
Classifier: License :: OSI Approved :: MIT License
Classifier: Operating System :: OS Independent
Classifier: Programming Language :: Python
